{
  "name": "Brian McNamara",
  "github": "mcnamarabrian",
  "twitter": "mcnamarabrian",
  "avatar": "https://avatars1.githubusercontent.com/u/17259?s=400&v=4",
  "bio": {
    "short": "Solutions Architect",
    "long": "Brian is a Solutions Architect focused on enabling customers to develop products and services using Vendia. Prior to Vendia, Brian worked as a serverless solutions architect at Amazon Web Services (AWS). He has experience helping start-ups and enterprises to solve infrastructure automation challenges."
  }
}
